alleai/__init__.py
alleai/core/__init__.py
alleai/core/client.py
alleai/core/exceptions.py
alleai/core/file.py
alleai/core/helper.py
alleai/core/logging_config.py
alleai/core/utils.py
alleai/models/__init__.py
alleai/models/audio.py
alleai/models/base.py
alleai/models/chat.py
alleai/models/image.py
alleai/models/video.py
alle_ai_sdk-2.0.0.dist-info/METADATA
alle_ai_sdk-2.0.0.dist-info/WHEEL
alle_ai_sdk-2.0.0.dist-info/licenses/LICENSE
alle_ai_sdk-2.0.0.dist-info/RECORD
